Workbook

Sheet Projections
B1: 13 Week Cash Flow Forcast
E5: Previous 4 Weeks | I5: 13 Week Projections
B6: Date at Start of Week | E6: =F6-7 -> 46041 | F6: =G6-7 -> 46048 | G6: =H6-7 -> 46055 | H6: =I6-7 -> 46062 | I6: 46069 | J6: =I6+7 -> 46076 | K6: =J6+7 -> 46083 | L6: =K6+7 -> 46090 | M6: =L6+7 -> 46097 | N6: =M6+7 -> 46104 | O6: =N6+7 -> 46111 | P6: =O6+7 -> 46118 | Q6: =P6+7 -> 46125 | ... U6: =T6+7 -> 46153
B7: Week Number | I7: Week 1 | J7: Week 2 | K7: Week 3 | L7: Week 4 | M7: Week 5 | N7: Week 6 | O7: Week 7 | P7: Week 8 | Q7: Week 9 | R7: Week 10 | S7: Week 11 | T7: Week 12 | U7: Week 13
B9: Beginning Bank Balance | E9: =E88-E86-E54 -> 99783.478 | F9: =F88-F86-F54 -> 128888.14 | G9: =G88-G86-G54 -> 211941.16 | H9: =H88-H86-H54 -> 275905.01 | I9: 250799.26 | J9: =I88 -> 274697.53 | K9: =J88 -> 276172.1 | L9: =K88 -> 274809.78 | M9: =L88 -> 271368.53 | N9: =M88 -> 273476.37 | O9: =N88 -> 272246.98 | P9: =O88 -> 273351.94 | Q9: =P88 -> 273965.37 | ... U9: =T88 -> 271227.37
B11: Cash Inflows
C12: AR Collected | E12: =SUM(E13:E45) -> 261924.06 | F12: =SUM(F13:F45) -> 239363.15 | G12: =SUM(G13:G45) -> 180447.95 | H12: =SUM(H13:H45) -> 153110.06 | I12: =SUM(I13:I45) -> 68798.12 | J12: =SUM(J13:J45) -> 95470 | K12: =SUM(K13:K45) -> 141297.49 | L12: =SUM(L13:L45) -> 99470 | ... U12: =SUM(U13:U45) -> 142000
D13: Blackfeet Nation | K13: 20000 | O13: 20000 | R13: 45000
D14: Blackfeet Nation (Medical) | F14: 28000
D15: Blackfeet Nation (Sukapi Lodge)
D16: Bristol Hospital Incorporated | H16: 50000 | K16: 50000 | M16: 50000 | O16: 50000 | Q16: 39700.3
D17: Chenega Government Mission Solutions | I17: 5104 | L17: 4000 | O17: 4000 | R17: 4000 | T17: 4000
D18: Cheyenne River Sioux Tribe
D19: Cheyenne River Sioux Tribe (Dental) | G19: 25424 | H19: 18160 | M19: 32000 | Q19: 32000 | U19: 32000
D20: Community Health Programs Inc. | G20: 51797.13 | J20: 20000 | K20: 12000 | L20: 20000 | M20: 11000 | N20: 20000 | O20: 12000 | P20: 20000 | Q20: 10000 | S20: 20000 | U20: 20000
D21: Fairfield Dental Associates
D22: Great Plains Tribal Leaders Health Board | E22: 115677.36 | F22: 49326.9 | G22: 8320 | H22: 17488.18 | I22: 37099.33 | J22: 45000 | L22: 45000 | N22: 45000 | O22: 37000 | P22: 45000 | R22: 45000 | T22: 45000
D23: Hamilton Dental Associates Inc.
D24: Integrative Emergency Services | I24: 4834.79 | L24: 4000 | O24: 3000 | Q24: 4000 | S24: 3000
D25: Kaiser Permanente Greater Southern Alameda Area | E25: 10200 | I25: 21760 | K25: 22000 | M25: 17000 | O25: 15000 | Q25: 20000 | S25: 8000 | U25: 6000
D26: Karuk Tribe Health & Human Services | E26: 24127.39 | F26: 39383.81 | G26: 14683.08 | H26: 22114.85 | K26: 11000 | N26: 14000 | Q26: 15200 | T26: 16400
D27: Klamath Health Partnership, INC
D28: Lone Peak Dental Group | E28: 32478.77 | J28: 10000 | M28: 8000 | O28: 5000 | R28: 5000
D29: Marshfield Clinic, Inc. and Marshfield Clinic Health System, Inc. | G29: 8518.75 | J29: 8500 | L29: 8500 | N29: 8500 | P29: 8500 | R29: 8500 | T29: 8500
D30: MCR Health, INC
D31: My Michigan | G31: 11970 | H31: 8977.5 | J31: 11970 | L31: 17970 | N31: 19230 | P31: 23840 | R31: 18970 | T31: 23840
D32: Pascua Yaqui Tribe | E32: 73782.58 | F32: 19506.28 | G32: 59734.99 | H32: 36369.53 | K32: 21000 | M32: 28000 | O32: 29600 | R32: 23000 | U32: 24000
D33: Ponca Tribe of Nebraska
D34: Ponca Tribe of Nebraska (Dental)
D35: Ponca Tribe of Nebraska (Medical)
D36: Sault Tribe Health Division | E36: 5657.96
D37: TD Dental LLC
D38: Tuolumne Me-Wuk Indian Health Center | F38: 97650
D39: United Indian Health Services
D40: United Indian Health Services (Del Norte)
D41: U.S. Nursing Corporation
D42: Wentworth-Douglass Hospital and Health Foundation | F42: 5496.16 | K42: 5297.49
D44: Other | N44: 10000 | O44: 50000 | P44: 30000 | Q44: 70000 | R44: 20000 | S44: 70000 | T44: 70000 | U44: 60000
C46: Other Income | E46: 0 | F46: 0 | G46: 0 | H46: =SUM(H47:H49) -> 0 | I46: =I47+I48 -> 0 | J46: =J47+J48 -> 0 | K46: =K47+K48 -> 0 | L46: =L47+L48 -> 0 | M46: =M47+M48 -> 0 | N46: =N47+N48 -> 0 | O46: =O47+O48 -> 0 | P46: =P47+P48 -> 0 | ... U46: =U47+U48 -> 0
D47: Travel Reimbursement
D48: New Billing Payments
C50: Line of Credit Advances | E50: 165000 | F50: 265000 | G50: 225000 | H50: =SUM(H51:H53) -> 200000 | I50: =SUM(I51:I53) -> 185000 | J50: =SUM(J51:J53) -> 190000 | K50: =SUM(K51:K53) -> 165000 | L50: =SUM(L51:L53) -> 200000 | M50: =SUM(M51:M53) -> 175000 | N50: =SUM(N51:N53) -> 210000 | O50: =SUM(O51:O53) -> 190000 | ... U50: =SUM(U51:U53) -> 225000
D51: Access Capital | E51: 190000 | F51: 145000 | G51: 155000 | H51: 200000 | I51: 185000 | J51: =MROUND((SUM(J60:J73)+SUM(J77:J84)), 5000) -> 190000 | K51: =MROUND((SUM(K60:K73)+SUM(K77:K84)), 5000) -> 165000 | L51: =MROUND((SUM(L60:L73)+SUM(L77:L84)), 5000) -> 200000 | M51: =MROUND((SUM(M60:M73)+SUM(M77:M84)), 5000) -> 175000 | N51: =MROUND((SUM(N60:N73)+SUM(N77:N84)), 5000) -> 210000 | O51: =MROUND((SUM(O60:O73)+SUM(O77:O84)), 5000) -> 190000 | P51: =MROUND((SUM(P60:P73)+SUM(P77:P84)), 5000) -> 210000 | Q51: =MROUND((SUM(Q60:Q73)+SUM(Q77:Q84)), 5000) -> 190000 | ... U51: =MROUND((SUM(U60:U73)+SUM(U77:U84)), 5000) -> 225000
D52: Other
B54: Total Cash Inflows | E54: =E12+E46+E50 -> 426924.06 | F54: =F12+F46+F50 -> 504363.15 | G54: =G12+G46+G50 -> 405447.95 | H54: =H50+H46+H12 -> 353110.06 | I54: =I12+I46+I50 -> 253798.12 | J54: =J12+J46+J50 -> 285470 | K54: =K12+K46+K50 -> 306297.49 | L54: =L12+L46+L50 -> 299470 | M54: =M12+M46+M50 -> 321000 | N54: =N12+N46+N50 -> 326730 | O54: =O12+O46+O50 -> 415600 | P54: =P12+P46+P50 -> 337340 | ... U54: =U12+U46+U50 -> 367000
B56: Cash Outflows
C57: Expenses & Accounts Payable | E57: =-SUM(E58:E75) -> -396989.18 | F57: =-SUM(F58:F75) -> -408017.02 | G57: =-SUM(G58:G75) -> -338536.54 | H57: =-SUM(H58:H75) -> -376172.72 | I57: =-SUM(I58:I75) -> -229476.41 | J57: =-SUM(J58:J75) -> -277715.43 | K57: =-SUM(K58:K75) -> -307454.81 | L57: =-SUM(L58:L75) -> -300979.94 | ... U57: =-SUM(U58:U75) -> -366500.73
D58: Access Captial (principal) | E58: =E47+E12-E59 -> 259185.76 | F58: =F47+F12-F59 -> 236860.72 | G58: =G47+G12-G59 -> 178561.45 | H58: =H47+H12-H59 -> 151509.36 | I58: =(I12+I47)-I59 -> 68078.867 | J58: =(J12+J47)-J59 -> 94471.905 | K58: =(K12+K47)-K59 -> 139820.29 | L58: =(L12+L47)-L59 -> 98430.086 | M58: =(M12+M47)-M59 -> 144473.64 | N58: =(N12+N47)-N59 -> 115509.64 | O58: =(O12+O47)-O59 -> 223241.45 | P58: =(P12+P47)-P59 -> 126008.72 | ... U58: =(U12+U47)-U59 -> 140515.45
D59: Access Captial (interest) | E59: =(E12+E47)*0.115/11 -> 2738.297 | F59: =(F12+F47)*0.115/11 -> 2502.4329 | G59: =(G12+G47)*0.115/11 -> 1886.5013 | H59: =(H12+H47)*0.115/11 -> 1600.6961 | I59: =(I12+I47)*0.115/11 -> 719.25307 | J59: =(J12+J47)*0.115/11 -> 998.09545 | K59: =(K12+K47)*0.115/11 -> 1477.201 | L59: =(L12+L47)*0.115/11 -> 1039.9136 | ... U59: =(U12+U47)*0.115/11 -> 1484.5455
D60: Ascen Payroll | E60: 29807.31 | F60: 37927 | G60: 29194.12 | H60: 45599.5 | I60: 21282.45 | J60: =SUM(F60:I60)/4 -> 33500.768 | K60: =(SUM(G60:J60)/4)*1.05 -> 34013.92 | L60: =(SUM(H60:K60)/4)*1.05 -> 35279.117 | M60: =(SUM(I60:L60)/4)*1.05 -> 32570.017 | N60: =(SUM(J60:M60)/4)*1.05 -> 35533.003 | O60: =(SUM(K60:N60)/4)*1.05 -> 36066.465 | P60: =(SUM(L60:O60)/4)*1.05 -> 36605.258 | Q60: =(SUM(M60:P60)/4)*1.05 -> 36953.37 | R60: =(SUM(N60:Q60)/4)*1.05 -> 38104 | ... U60: =(SUM(Q60:T60)/4)*1.05 -> 40248.378
D61: Ascen Payroll Taxes & Fees | E61: =(E60+E63)*0.014 -> 1436.3705 | F61: =(F60+F63)*0.014 -> 1569.6458 | G61: =(G60+G63)*0.014 -> 1388.4423 | H61: =(H60+H63)*0.014 -> 1990.2197 | I61: =(I60+I63)*0.014 -> 1414.4827 | J61: =(J60+J63)*0.014 -> 1628.423 | K61: =(K60+K63)*0.014 -> 1635.9047 | L61: =(L60+L63)*0.014 -> 1666.6327 | ... U61: =(U60+U63)*0.014 -> 2145.8261
D62: Consultants Exchange Management Services Inc. | E62: 23854.91 | F62: 23854.91 | G62: 36870.53 | H62: 76329.46 | I62: 33578.06 | J62: ='Internal Payroll'!Y22 -> 43671.078 | K62: ='Internal Payroll'!Z22 -> 37671.078 | L62: ='Internal Payroll'!AA22 -> 47671.078 | M62: ='Internal Payroll'!AB22 -> 37671.078 | N62: ='Internal Payroll'!AC22 -> 63671.078 | O62: ='Internal Payroll'!AD22 -> 41608.588 | P62: ='Internal Payroll'!AE22 -> 57609.588 | Q62: ='Internal Payroll'!AF22 -> 41608.588 | ... U62: ='Internal Payroll'!AJ22 -> 41608.588
D63: Contractors/Payroll | E63: 72790.58 | F63: 74190.56 | G63: 69980.33 | H63: 96559.05 | I63: 79752.03 | J63: ='Future Sales'!M28*0.8 -> 82815.163 | K63: ='Future Sales'!N28*0.8 -> 82836.418 | L63: ='Future Sales'!O28*0.8 -> 83766.073 | M63: ='Future Sales'!P28*0.8 -> 83305.779 | N63: ='Future Sales'!Q28*0.8 -> 82316.313 | O63: ='Future Sales'!R28*0.8 -> 84255.482 | P63: ='Future Sales'!S28*0.8 -> 82786.388 | Q63: ='Future Sales'!T28*0.8 -> 92405.273 | ... U63: ='Future Sales'!X28*0.8 -> 113024.92
D64: CC Payments (Generally Travel Reimbursement) | E64: 5000 | F64: 30000 | G64: 20000 | I64: 15000 | J64: 20000 | K64: 10000 | L64: 25000 | M64: 15000 | N64: 20000 | O64: 25000 | P64: 20000 | Q64: 15000 | R64: 20000 | S64: 15000 | T64: 20000 | U64: 25000
D65: Insurance & Licenses | I65: 2473.02 | M65: 2473.02 | Q65: 2473.02 | U65: 2473.02
D66: New Payroll
D67: Other Contractors
D68: Prepaid Expenses
D69: Professional Services | I69: 6431.25 | L69: 6431.25 | P69: 6431.25 | T69: 6431.25
D70: Rent - 725 Suites LLC | I70: 747 | L70: 750 | N70: 747 | P70: 750 | R70: 747 | T70: 750
D71: Subscriptions & Software | E71: 2175.95 | F71: 574.76 | G71: 1.99 | H71: 772.56
D72: Travel Expenses
D73: Utilities & Phone | F73: 536.99 | G73: 23.18 | H73: 1339.37
D74: VMS Fees | E74: =(E31/0.95)-E31 -> 0 | F74: =(F31/0.95)-F31 -> 0 | G74: =(G31/0.95)-G31 -> 630 | H74: =(H31/0.95)-H31 -> 472.5 | I74: =(I31/0.95)-I31 -> 0 | J74: =(J31/0.95)-J31 -> 630 | K74: =(K31/0.95)-K31 -> 0 | L74: =(L31/0.95)-L31 -> 945.78947 | ... U74: =(U31/0.95)-U31 -> 0
C76: Other Expenses | E76: =-SUM(E77:E85) -> -830.22 | F76: =-SUM(F77:F85) -> -13293.11 | G76: =-SUM(G77:G85) -> -2947.56 | H76: =-SUM(H77:H85) -> -2043.09 | I76: =-SUM(I77:I85) -> -423.44 | J76: =-SUM(J77:J85) -> -6280 | K76: =-SUM(K77:K85) -> -205 | L76: =-SUM(L77:L85) -> -1931.307 | ... U76: =-SUM(U77:U85) -> -2129.266
D77: Advertising | G77: 2667.56
D78: Bank Fee | H78: 1839.34 | L78: =H78*1.05 -> 1931.307 | P78: =L78*1.05 -> 2027.8724 | U78: =P78*1.05 -> 2129.266
D79: Distributions
D80: New Software | F80: 12000 | J80: 6000 | N80: 6000 | R80: 6000
D81: Office Supplies | F81: 269.34 | H81: 203.75 | I81: 423.44 | K81: 205 | M81: 250 | N81: 300 | P81: 250 | Q81: 325 | S81: 300 | T81: 375
D82: Licensing & Fees | E82: 830.22 | F82: 1023.77
D83: Loan Fees | G83: 280 | J83: 280 | O83: 280 | S83: 280
D84: Reimbursement Expenses (generally travel not on CC)
B86: Total Cash Outflows | E86: =E76+E57 -> -397819.4 | F86: =F76+F57 -> -421310.13 | G86: =G76+G57 -> -341484.1 | H86: =H57+H76 -> -378215.81 | I86: =I76+I57 -> -229899.85 | J86: =J76+J57 -> -283995.43 | K86: =K76+K57 -> -307659.81 | L86: =L76+L57 -> -302911.25 | M86: =M76+M57 -> -318892.15 | N86: =N76+N57 -> -327959.39 | O86: =O76+O57 -> -414495.04 | P86: =P76+P57 -> -336726.58 | ... U86: =U76+U57 -> -368629.99
B88: Ending Bank Balance | E88: =F9 -> 128888.14 | F88: =G9 -> 211941.16 | G88: =H9 -> 275905.01 | H88: =I9 -> 250799.26 | I88: =I9+I54+I86 -> 274697.53 | J88: =J9+J54+J86 -> 276172.1 | K88: =K9+K54+K86 -> 274809.78 | L88: =L9+L54+L86 -> 271368.53 | M88: =M9+M54+M86 -> 273476.37 | N88: =N9+N54+N86 -> 272246.98 | O88: =O9+O54+O86 -> 273351.94 | P88: =P9+P54+P86 -> 273965.37 | ... U88: =U9+U54+U86 -> 269597.37
B91: Starting Loan Balance | E91: 470623.96 | F91: 398669.9 | G91: 310443 | H91: 284995.05 | I91: 331884.99 | J91: =I91+I51-(SUM(I13:I45))+I78+I83 -> 448086.87 | K91: =J91+J51-(SUM(J13:J45))+J78+J83 -> 542896.87 | L91: =K91+K51-(SUM(K13:K45))+K78+K83 -> 566599.38 | M91: =L91+L51-(SUM(L13:L45))+L78+L83 -> 669060.69 | N91: =M91+M51-(SUM(M13:M45))+M78+M83 -> 698060.69 | O91: =N91+N51-(SUM(N13:N45))+N78+N83 -> 791330.69 | P91: =O91+O51-(SUM(O13:O45))+O78+O83 -> 756010.69 | Q91: =P91+P51-(SUM(P13:P45))+P78+P83 -> 840698.56 | ... U91: =T91+T51-(SUM(T13:T45))+T78+T83 -> 1041868.3
B93: Weekly P&L (meaning what was billed vs what was spent -> this is not direct yet because we bill 1099 the week before the payroll is paid) | E93: ='Future Sales'!G26-sum(E60:E75)-sum(E77:E84) -> 59438.82 | F93: ='Future Sales'!H26-sum(F60:F75)-sum(F77:F84) -> 14792.59 | G93: ='Future Sales'!I26-sum(G60:G75)-sum(G77:G84) -> 32199.635 | H93: ='Future Sales'!J26-sum(H60:H75)-sum(H77:H84) -> -35768.676 | I93: ='Future Sales'!K26-sum(I60:I75)-sum(I77:I84) -> 19143.187 | J93: ='Future Sales'!L26-sum(J60:J75)-sum(J77:J84) -> -4224.5814 | K93: ='Future Sales'!M26-sum(K60:K75)-sum(K77:K84) -> 14869.27 | L93: ='Future Sales'!N26-sum(L60:L75)-sum(L77:L84) -> -22165.377 | ... U93: ='Future Sales'!W26-sum(U60:U75)-sum(U77:U84) -> 3500.121
B95: Amount Inelligible Over 90 | E95: 103272 | F95: 82666 | G95: 105721 | H95: 133051 | I95: 111121 | J95: =I95-J16+10000 -> 121121 | K95: =J95-K16+10000 -> 81121 | L95: =K95-L16+10000 -> 91121 | M95: =L95-M16+10000 -> 51121 | N95: =M95-N16+10000 -> 61121 | O95: =N95-O16+10000 -> 21121 | P95: =O95-P16+10000 -> 31121 | Q95: =P95-Q16+10000 -> 1420.7 | ... U95: =T95-U16+10000 -> 41420.7
B97: Amount Inelligible Distribution Limits - Tribal | H97: 2256 | I97: 27317 | J97: =I97-(I22*0.21)+3000 -> 22526.141 | K97: =J97-(J22*0.2)+3000 -> 16526.141 | L97: =K97-(K22*0.2)+3000 -> 19526.141 | M97: =L97-(L22*0.2)+3000 -> 13526.141 | N97: =M97-(M22*0.2)+3000 -> 16526.141 | O97: =N97-(N22*0.2)+3000 -> 10526.141 | P97: =O97-(O22*0.18)+3000 -> 6866.1407 | Q97: =P97-(P22*0.18)+3000 -> 1766.1407 | R97: =Q97-(Q22*0.18)+3000 -> 4766.1407 | S97: =R97-(R22*0.18)+3000 -> -333.8593 | T97: =S97-(S22*0.2)+3000 -> 2666.1407 | U97: =T97-(T22*0.2)+3000 -> -3333.8593
B99: Amount Inelligible Distribution Limits - Traditional

Sheet Draw

Sheet AR_by_week
A1: Payer | B1: 6/9/25 | C1: 6/16/25 | D1: 6/23/25 | E1: 6/30/25 | F1: 7/7/25 | G1: 7/14/25 | H1: 7/21/25 | I1: 7/28/25 | J1: 8/4/25 | K1: 8/11/25 | L1: 8/18/25 | M1: 8/25/25 | N1: 9/1/25 | O1: 9/8/25 | P1: 9/15/25 | Q1: 9/22/25 | R1: 46294 | S1: 46301 | T1: 46308 | U1: 46315 | V1: 46322 | W1: 46329 | X1: 46336 | Y1: TOTAL
A2: Blackfeet Nation (Medical) | E2: 21182.89 | F2: 13381.13 | G2: 9213.87 | H2: 18259.5 | J2: 18959.5 | K2: 27288.68 | L2: 18718.45 | M2: 21597.8 | N2: 28689.53 | O2: 8725.5 | P2: 26240.2 | Q2: 14935.48 | Y2: =SUM(B2:U2) -> 227192.53
A3: Bristol Hospital Incorporated | H3: 19000 | I3: 34200 | J3: 28268.74 | L3: 1155.49 | M3: 26600 | O3: 26600 | P3: 29521.07 | Q3: 27941.81 | Y3: =SUM(B3:U3) -> 193287.11
A4: Cheyenne River Sioux Tribe (Dental) | F4: 5760 | G4: 9600 | H4: 9600 | I4: 9600 | J4: 9600 | K4: 9600 | L4: 3840 | M4: 9600 | N4: 7680 | O4: 7680 | P4: 9600 | Q4: 9600 | Y4: =SUM(B4:U4) -> 101760
A5: Great Plains Tribal Leaders Health Board | M5: 16846.61 | N5: 12350 | O5: 18141.85 | P5: 29779.65 | Q5: 30391.44 | Y5: =SUM(B5:U5) -> 107509.55
A6: Hamilton Dental Associates Inc. | B6: 3717.94 | C6: 7371.28 | D6: 5528.46 | E6: 7371.28 | F6: 5528.46 | G6: 5528.46 | Y6: =SUM(B6:U6) -> 35045.88
A7: Kaiser Permanente Greater Southern Alameda Area | Q7: 13770 | Y7: =SUM(B7:U7) -> 13770
A8: Karuk Tribe | K8: 7541.7 | L8: 7326.7 | Q8: 16503.3 | Y8: =SUM(B8:U8) -> 31371.7
A9: LifePoint Corporate Services | H9: 273 | Y9: =SUM(B9:U9) -> 273
A10: Lone Peak Dental Group | Y10: =SUM(B10:U10) -> 0
A11: MCR Health, INC | O11: 12000 | P11: 15000 | Q11: 15000 | Y11: =SUM(B11:U11) -> 42000
A12: Marshfield Clinic, Inc. and Marshfield Clinic Health System, Inc. | M12: 59047 | N12: 27950 | O12: 55012.5 | P12: 87794.17 | Q12: 15800 | Y12: =SUM(B12:U12) -> 245603.67
A13: Pascua Yaqui Tribe | N13: 10126.81 | O13: 7892.23 | P13: 10258.76 | Q13: 6459.61 | Y13: =SUM(B13:U13) -> 34737.41
A14: Ponca Tribe of Nebraska (Medical) | F14: 7985 | Y14: =SUM(B14:U14) -> 7985
A15: Sault Tribe Health Division (Sault Ste. Marie - Medical) | P15: 6588.11 | Q15: 4932.2 | Y15: =SUM(B15:U15) -> 11520.31
A16: Sault Tribe Health Division (St. Ignace) | P16: 3560 | Q16: 12650.25 | Y16: =SUM(B16:U16) -> 16210.25
A17: Shasta Community Health Center | M17: 8032 | Y17: =SUM(B17:U17) -> 8032
A18: TD Dental LLC | K18: 20 | L18: 3439.13 | M18: 3248 | Q18: 434.82 | Y18: =SUM(B18:U18) -> 7141.95
A19: United Indian Health Services (Del Norte) | Q19: 7257.96 | Y19: =SUM(B19:U19) -> 7257.96
A20: Wentworth-Douglass Hospital and Health Foundation | E20: 351.98 | G20: 763.74 | K20: 132 | M20: 19090 | N20: 19650 | P20: 80558.45 | Q20: 43425 | Y20: =SUM(B20:U20) -> 163971.17
A22: TOTAL REMAINING | B22: =SUM(B2:B20) -> 3717.94 | C22: =SUM(C2:C20) -> 7371.28 | D22: =SUM(D2:D20) -> 5528.46 | E22: =SUM(E2:E20) -> 28906.15 | F22: =SUM(F2:F20) -> 32654.59 | G22: =SUM(G2:G20) -> 25106.07 | H22: =SUM(H2:H20) -> 47132.5 | I22: =SUM(I2:I20) -> 43800 | ... Q22: =SUM(Q2:Q20) -> 219101.87 | Y22: =SUM(B22:U22) -> 1254669.5

Sheet Future Sales
A1: Payer | B1: 45915 | C1: 45922 | D1: 45929 | E1: 45936 | F1: 45943 | G1: 45950 | H1: 45957 | I1: 45964 | J1: 45971 | K1: 45978 | L1: 45985 | M1: 45992 | N1: 45999 | O1: 46006 | P1: 46013 | Q1: 46020 | R1: 46027 | S1: 46034 | T1: 46041 | U1: 46048 | V1: 46055 | W1: 46062 | X1: 46069 | Y1: 46076 | Z1: 46083 | AA1: 46090 | AB1: 46097
A2: Blackfeet Nation (Medical) | B2: 26240.2 | C2: 14935.48 | D2: =(B2+C2)/2 -> 20587.84 | E2: =(C2+D2)/2 -> 17761.66 | F2: =(D2+E2)/2 -> 19174.75 | G2: =(E2+F2)/2 -> 18468.205 | H2: =(F2+G2)/2 -> 18821.478 | I2: =(G2+H2)/2 -> 18644.841 | J2: =(H2+I2)/2 -> 18733.159 | K2: =(I2+J2)/2 -> 18689 | ... AB2: =(Z2+AA2)/2 -> 18703.72
A3: Bristol Hospital Incorporated | B3: 29521.07 | C3: 27941.81 | D3: =C3*1.02 -> 28500.646 | E3: =D3*0.98 -> 27930.633 | F3: =E3*1.02 -> 28489.246 | G3: =F3*0.98 -> 27919.461 | H3: =G3*1.02 -> 28477.85 | I3: =H3*0.98 -> 27908.293 | J3: =I3*1.02 -> 28466.459 | K3: =J3*0.98 -> 27897.13 | L3: =K3*1.02 -> 28455.073 | M3: =L3*0.98 -> 27885.971 | N3: =M3*1.02 -> 28443.69 | O3: =N3*0.98 -> 27874.817 | P3: =O3*1.02 -> 28432.313 | Q3: =P3*0.98 -> 27863.667 | R3: =Q3*1.02 -> 28420.94 | S3: =R3*0.98 -> 27852.521 | T3: =S3*1.02 -> 28409.572 | U3: =T3*0.98 -> 27841.38 | V3: =U3*1.02 -> 28398.208 | W3: =V3*0.98 -> 27830.244 | X3: =W3*1.02 -> 28386.849 | Y3: =X3*0.98 -> 27819.112 | Z3: =Y3*1.02 -> 28375.494 | AA3: =Z3*0.98 -> 27807.984 | AB3: =AA3*1.02 -> 28364.144
A4: Cheyenne River Sioux Tribe (Dental) | B4: 9600 | C4: 9600 | D4: 9600 | E4: 9600 | F4: 9600 | G4: 9600 | H4: 9600 | I4: 9600 | J4: 9600 | K4: 9600 | L4: 9600 | M4: 9600 | N4: 9600 | O4: 9600 | P4: 9600 | Q4: 9600 | R4: 9600 | S4: 9600 | T4: 9600 | U4: 9600 | V4: 9600 | W4: 9600 | X4: 9600 | Y4: 9600 | Z4: 9600 | AA4: 9600 | AB4: 9600
A5: Great Plains Tribal Leaders Health Board | B5: 29779.65 | C5: 30391.44 | D5: =C5*1.02 -> 30999.269 | E5: =D5*0.98 -> 30379.283 | F5: =E5*1.02 -> 30986.869 | G5: =F5*0.98 -> 30367.132 | H5: =G5*1.02 -> 30974.474 | I5: =H5*0.78 -> 24160.09 | J5: =I5*1.02 -> 24643.292 | K5: =J5*0.98 -> 24150.426 | L5: =K5*1.02 -> 24633.434 | M5: =L5*0.98 -> 24140.766 | N5: =M5*1.02 -> 24623.581 | O5: =N5*0.98 -> 24131.109 | P5: =O5*1.02 -> 24613.732 | Q5: =P5*0.98 -> 24121.457 | R5: =Q5*1.02 -> 24603.886 | S5: =R5*0.98 -> 24111.808 | T5: =S5*1.02 -> 24594.045 | U5: =T5*0.98 -> 24102.164 | V5: =U5*1.02 -> 24584.207 | W5: =V5*0.98 -> 24092.523 | X5: =W5*1.02 -> 24574.373 | Y5: =X5*0.98 -> 24082.886 | Z5: =Y5*1.02 -> 24564.544 | AA5: =Z5*0.98 -> 24073.253 | AB5: =AA5*1.02 -> 24554.718
A6: Hamilton Dental Associates Inc.
A7: Kaiser Permanente Greater Southern Alameda Area | C7: 13770 | D7: 13770 | E7: 13770 | F7: 13770 | G7: 13770 | H7: 13770 | I7: 13770 | J7: 13770 | K7: 13770 | L7: 13770 | M7: 13770 | N7: 13770 | O7: 13770 | P7: 13770 | Q7: 13770 | R7: 13770 | S7: 13770 | T7: 13770 | U7: 13770 | V7: 13770 | W7: 13770 | X7: 13770 | Y7: 13770 | Z7: 13770 | AA7: 13770 | AB7: 13770
A8: Karuk Tribe | C8: 16503.3 | D8: 16503.3 | E8: 16503.3 | F8: 16503.3 | G8: 16503.3 | H8: 16503.3 | I8: 20503.3 | J8: 20503.3 | K8: 20503.3 | L8: 20503.3 | M8: 20503.3 | N8: 20503.3 | O8: 20503.3 | P8: 20503.3 | Q8: 20503.3 | R8: 20503.3 | S8: 20503.3 | T8: 20503.3 | U8: 20503.3 | V8: 20503.3 | W8: 20503.3 | X8: 20503.3 | Y8: 20503.3 | Z8: 20503.3 | AA8: 20503.3 | AB8: 20503.3
A9: LifePoint Corporate Services
A10: MCR Health, INC | B10: 15000 | C10: 15000 | D10: 15000 | E10: 15000 | F10: 15000 | G10: 15000 | H10: 15000 | I10: 15000 | J10: 15000 | K10: 15000 | L10: 15000 | M10: 15000 | N10: 15000 | O10: 15000 | P10: 15000 | Q10: 15000 | R10: 15000 | S10: 15000 | T10: 15000 | U10: 15000 | V10: 15000 | W10: 15000 | X10: 15000 | Y10: 15000 | Z10: 15000 | AA10: 15000 | AB10: 15000
A11: Marshfield Clinic, Inc. and Marshfield Clinic Health System, Inc. | B11: 87794.17 | C11: 15800 | D11: 15800 | E11: 15800 | F11: 15800 | G11: 15800 | H11: 15800 | I11: 15800 | J11: 15800 | K11: 15800 | L11: 15800 | M11: 15800 | N11: 15800 | O11: 15800 | P11: 15800 | Q11: 15800 | R11: 15800 | S11: 15800 | T11: 15800 | U11: 15800 | V11: 15800 | W11: 15800 | X11: 15800 | Y11: 15800 | Z11: 15800 | AA11: 15800 | AB11: 15800
A12: Pascua Yaqui Tribe | B12: 10258.76 | C12: 6459.61 | D12: =(B12+C12)/2 -> 8359.185 | E12: =(C12+D12)/2 -> 7409.3975 | F12: =(D12+E12)/2 -> 7884.2913 | G12: =(E12+F12)/2 -> 7646.8444 | H12: =(F12+G12)/2 -> 7765.5678 | I12: =(G12+H12)/2 -> 7706.2061 | J12: =(H12+I12)/2 -> 7735.887 | K12: =(I12+J12)/2 -> 7721.0465 | ... AB12: =(Z12+AA12)/2 -> 7725.9934
A13: Ponca Tribe of Nebraska (Medical)
A14: Sault Tribe Health Division (Sault Ste. Marie - Medical) | B14: 6588.11 | C14: 4932.2 | D14: =(B14+C14)/2 -> 5760.155 | E14: =(C14+D14)/2 -> 5346.1775 | F14: =(D14+E14)/2 -> 5553.1663 | G14: =(E14+F14)/2 -> 5449.6719 | H14: =(F14+G14)/2 -> 5501.4191 | I14: =(G14+H14)/2 -> 5475.5455 | J14: =(H14+I14)/2 -> 5488.4823 | K14: =(I14+J14)/2 -> 5482.0139 | ... AB14: =(Z14+AA14)/2 -> 5484.17
A15: Sault Tribe Health Division (St. Ignace) | B15: 3560 | C15: 12650.25 | D15: =(B15+C15)/2 -> 8105.125 | E15: =(C15+D15)/2 -> 10377.688 | F15: =(D15+E15)/2 -> 9241.4062 | G15: =(E15+F15)/2 -> 9809.5469 | H15: =(F15+G15)/2 -> 9525.4766 | I15: =(G15+H15)/2 -> 9667.5117 | J15: =(H15+I15)/2 -> 9596.4941 | K15: =(I15+J15)/2 -> 9632.0029 | ... AB15: =(Z15+AA15)/2 -> 9620.1666
A16: Shasta Community Health Center
A17: TD Dental LLC | C17: 434.82
A18: United Indian Health Services (Del Norte) | C18: 7257.96
A19: US Nursing
A20: Wentworth-Douglass Hospital and Health Foundation | B20: 80558.45 | C20: 43425 | D20: =(B20+C20)/2 -> 61991.725 | E20: =(C20+D20)/2 -> 52708.363 | F20: =(D20+E20)/2 -> 57350.044 | G20: 25000 | H20: 25000 | I20: 25000 | J20: 20000 | K20: 12000 | L20: 15000 | M20: 13000 | N20: 12000 | O20: 15000 | P20: 13000 | Q20: 12000 | R20: 15000 | S20: 13000 | T20: 12000 | U20: 15000 | V20: 13000 | W20: 12000 | X20: 15000 | Y20: 13000 | Z20: 12000 | AA20: 15000 | AB20: 13000
A22: NEW CLIENTS | T22: 20000 | U22: 30000 | V22: 40000 | W22: 50000 | X22: 60000 | Y22: 70000 | Z22: 80000 | AA22: 90000 | AB22: 100000
A26: TOTAL REMAINING | B26: =SUM(B2:B20) -> 298900.41 | C26: =SUM(C2:C20) -> 219101.87 | D26: =SUM(D2:D20) -> 234977.24 | E26: =SUM(E2:E20) -> 222586.5 | F26: =SUM(F2:F20) -> 229353.07 | G26: =SUM(G2:G20) -> 195334.16 | H26: =SUM(H2:H20) -> 196739.57 | I26: =SUM(I2:I20) -> 193235.79 | ... R26: =SUM(R2:R20) -> 184232.25 | S26: =SUM(S2:S25) -> 181171.64 | T26: =SUM(T2:T25) -> 201210.99 | U26: =SUM(U2:U25) -> 213150.88 | V26: =SUM(V2:V25) -> 222189.77 | W26: =SUM(W2:W25) -> 230130.11 | X26: =SUM(X2:X25) -> 244168.57 | Y26: =SUM(Y2:Y25) -> 251109.35 | Z26: =SUM(Z2:Z25) -> 261147.39 | ... AB26: =SUM(AB2:AB25) -> 282126.21
A28: Payroll | D28: =(D26-8700)*0.72 -> 162919.62 | E28: =(E26-8700)*0.72 -> 153998.28 | F28: =(F26-8700)*0.72 -> 158870.21 | G28: =(G26-8700)*0.72 -> 134376.6 | H28: =(H26-8700)*0.72 -> 135388.49 | I28: =(I26-8700)*0.72 -> 132865.77 | J28: =(J26-8700)*0.6 -> 108382.24 | K28: =(K26-8700)*0.6 -> 102926.95 | L28: =(L26-8700)*0.6 -> 105360.51 | M28: =(M26-8700)*0.6 -> 103518.95 | N28: =(N26-8700)*0.6 -> 103545.52 | O28: =(O26-8700)*0.6 -> 104707.59 | P28: =(P26-8700)*0.6 -> 104132.22 | Q28: =(Q26-8700)*0.6 -> 102895.39 | ... AB28: =(AB26-8700)*0.6 -> 164055.73
A29: W2 Payroll
A30: 1099 Payroll

Sheet Internal Payroll
A1: Last Name | B1: First Name | C1: Role | D1: Commissions | E1: 45912 | F1: 45919 | G1: 45926 | H1: 45933 | I1: 45940 | J1: 45947 | K1: 45954 | L1: 45961 | M1: 45968 | N1: 45975 | O1: 45982 | P1: 45989 | Q1: 45996 | R1: 46003 | S1: 46010 | T1: 46017 | U1: 46024 | V1: 46031 | W1: 46038 | X1: 46045 | Y1: 46052 | Z1: 46059 | AA1: 46066 | AB1: 46073 | AC1: 46080 | AD1: 46087 | AE1: 46094 | AF1: 46101 | AG1: 46108 | AH1: 46115 | AI1: 46122 | AJ1: 46129 | AK1: 46136 | AL1: 46143 | AM1: 46150
A2: Smith | B2: Aaron | E2: 2250 | F2: 2250 | G2: 2250 | H2: 2250 | I2: 2250 | J2: 2250 | K2: 2250 | L2: 2250 | M2: 2250 | N2: 2250 | O2: 2250 | P2: 2250 | Q2: 2250 | R2: 2250 | S2: 2250 | T2: 2250 | U2: 2250 | V2: 2250 | W2: 2250 | X2: 2250 | Y2: 2250 | Z2: 2250 | AA2: 2250 | AB2: 2250 | AC2: 2250 | AD2: 2250 | AE2: 2250 | AF2: 2250 | AG2: 2250 | AH2: 2250 | AI2: 2250 | AJ2: 2250 | AK2: 2250 | AL2: 2250 | AM2: 2250
A3: Cassidy | B3: Bob | D3: Yes | E3: 1687.78 | F3: 1688.78 | G3: 1688.78 | H3: 1688.78 | I3: 1688.78 | J3: 1688.78 | K3: 1688.78 | L3: 1687.6 | M3: 1688.78 | N3: 1688.78 | O3: 1688.78 | P3: 1688.78 | Q3: 1688.78 | R3: 1688.78 | S3: 1688.78 | T3: 1688.78 | U3: 1688.78 | V3: 1688.78 | W3: 1688.78 | X3: 1688.78 | Y3: 1688.78 | Z3: 1688.78 | AA3: 1688.78 | AB3: 1688.78 | AC3: 1688.78 | AD3: 1688.78 | AE3: 1688.78 | AF3: 1688.78 | AG3: 1688.78 | AH3: 1688.78 | AI3: 1688.78 | AJ3: 1688.78 | AK3: 1688.78 | AL3: 1688.78 | AM3: 1688.78
A4: Noonan | B4: Bridget | F4: 1912.51 | G4: 1912.51 | H4: 1912.51 | I4: 1912.51 | J4: 1912.51 | K4: 1912.51 | L4: =320+1912.51 -> 2232.51 | M4: 1912.51 | N4: 1912.51 | O4: 1912.51 | P4: 1912.51 | Q4: 1912.51 | R4: 1912.51 | S4: 1912.51 | T4: 1912.51 | U4: 1912.51 | V4: 1912.51 | W4: 1912.51 | X4: 1912.51 | Y4: 1912.51 | Z4: 1912.51 | AA4: 1912.51 | AB4: 1912.51 | AC4: 1912.51 | AD4: 1912.51 | AE4: 1912.51 | AF4: 1912.51 | AG4: 1912.51 | AH4: 1912.51 | AI4: 1912.51 | AJ4: 1912.51 | AK4: 1912.51 | AL4: 1912.51 | AM4: 1912.51
A5: Bradley | B5: Chase | E5: 1350.18 | F5: 1350.18 | G5: 1350.18 | H5: 1350.18 | I5: 1350.18 | J5: 1350.18 | K5: 1350.18 | L5: 1350.18 | M5: 1350.18 | N5: 1350.18 | O5: 1350.18 | P5: 1350.18 | Q5: 1350.18 | R5: 1350.18 | S5: 1350.18 | T5: 1350.18 | U5: 1350.18 | V5: 1350.18 | W5: 1350.18 | X5: 1350.18 | Y5: 1350.18 | Z5: 1350.18 | AA5: 1350.18 | AB5: 1350.18 | AC5: 1350.18 | AD5: 1350.18 | AE5: 1350.18 | AF5: 1350.18 | AG5: 1350.18 | AH5: 1350.18 | AI5: 1350.18 | AJ5: 1350.18 | AK5: 1350.18 | AL5: 1350.18 | AM5: 1350.18
A6: Smaltz | B6: Christine | D6: Yes | E6: 1800.18 | F6: =1801.18+211.34 -> 2012.52 | G6: 1801.18 | H6: 1801.18 | I6: 1801.18 | J6: 1801.18 | K6: 1801.18 | L6: 1800 | M6: 1801.18 | N6: 1801.18 | O6: 1801.18 | P6: 1801.18 | Q6: 1801.18 | R6: 1801.18 | S6: 1801.18 | T6: 1801.18 | U6: 1801.18 | V6: 1801.18 | W6: 1801.18 | X6: 1801.18 | Y6: 1801.18 | Z6: 1801.18 | AA6: 1801.18 | AB6: 1801.18 | AC6: 1801.18 | AD6: 1801.18 | AE6: 1801.18 | AF6: 1801.18 | AG6: 1801.18 | AH6: 1801.18 | AI6: 1801.18 | AJ6: 1801.18 | AK6: 1801.18 | AL6: 1801.18 | AM6: 1801.18
A7: Lain | B7: Madison | F7: 1237.51 | G7: 1237.51 | H7: 1237.51 | I7: 1237.51 | J7: 1237.51 | K7: 1237.51 | L7: 1237.51 | M7: 1237.51 | N7: 1237.51 | O7: 1237.51 | P7: 1237.51 | Q7: 1237.51 | R7: 1237.51 | S7: 1237.51 | T7: 1237.51 | U7: 1237.51 | V7: 1237.51 | W7: 1237.51 | X7: 1237.51 | Y7: 1237.51 | Z7: 1237.51 | AA7: 1237.51 | AB7: 1237.51 | AC7: 1237.51 | AD7: 1237.51 | AE7: 1237.51 | AF7: 1237.51 | AG7: 1237.51 | AH7: 1237.51 | AI7: 1237.51 | AJ7: 1237.51 | AK7: 1237.51 | AL7: 1237.51 | AM7: 1237.51
A8: Schroeder | B8: Megan | E8: 1912.5 | F8: 1912.5 | G8: 1912.5 | H8: 1912.5 | I8: 1912.5 | J8: 1912.5 | K8: 1912.5 | L8: 765
A9: Ryan | B9: Michael | D9: Yes | E9: 1575.15 | F9: 1576.15 | G9: 1576.15 | H9: 1576.15 | I9: 1576.15 | J9: 1576.15 | K9: 1576.15 | L9: 1575.01 | M9: 1576.15 | N9: 1576.15 | O9: 1576.15 | P9: 1576.15 | Q9: 1576.15 | R9: 1576.15 | S9: 1576.15 | T9: 1576.15 | U9: 1576.15 | V9: 1576.15 | W9: 1576.15 | X9: 1576.15 | Y9: 1576.15 | Z9: 1576.15 | AA9: 1576.15 | AB9: 1576.15 | AC9: 1576.15 | AD9: 1576.15 | AE9: 1576.15 | AF9: 1576.15 | AG9: 1576.15 | AH9: 1576.15 | AI9: 1576.15 | AJ9: 1576.15 | AK9: 1576.15 | AL9: 1576.15 | AM9: 1576.15
A10: Timmons | B10: Michael | D10: Yes | E10: 1812.51 | F10: 1912.51 | G10: 1812.51 | H10: 1812.51 | I10: 1812.51 | J10: 1812.51 | K10: 1812.51 | L10: 1912.51 | M10: 1912.51 | N10: 1912.51 | O10: 1912.51 | P10: 1912.51 | Q10: 1912.51 | R10: 1912.51 | S10: 1912.51 | T10: 1912.51 | U10: 1912.51 | V10: 1912.51 | W10: 1912.51 | X10: 1912.51 | Y10: 1912.51 | Z10: 1912.51 | AA10: 1912.51 | AB10: 1912.51 | AC10: 1912.51 | AD10: 1912.51 | AE10: 1912.51 | AF10: 1912.51 | AG10: 1912.51 | AH10: 1912.51 | AI10: 1912.51 | AJ10: 1912.51 | AK10: 1912.51 | AL10: 1912.51 | AM10: 1912.51
A11: Lemay | B11: Nick | C11: Vice President of Inpatient Services | H11: =100000/52 -> 1923.0769 | I11: =100000/52 -> 1923.0769 | J11: =100000/52 -> 1923.0769 | K11: =100000/52 -> 1923.0769 | L11: 2250 | M11: 6345 | N11: 2250 | O11: 2250 | P11: =(100000/52)+3500 -> 5423.0769 | Q11: =100000/52 -> 1923.0769 | R11: =100000/52 -> 1923.0769 | S11: =100000/52 -> 1923.0769 | T11: =100000/52 -> 1923.0769 | U11: =100000/52 -> 1923.0769 | V11: =100000/52 -> 1923.0769 | W11: =100000/52 -> 1923.0769 | X11: =100000/52 -> 1923.0769 | ... AM11: =100000/52 -> 1923.0769
A12: Dargusch | B12: Shawn | E12: 3937.51 | F12: 3937.51 | G12: 3937.51 | H12: 3937.51 | I12: 3937.51 | J12: 3937.51 | K12: 3937.51 | L12: 3937.51 | M12: 3937.51 | N12: 3937.51 | O12: 3937.51 | P12: 3937.51 | Q12: 3937.51 | R12: 3937.51 | S12: 3937.51 | T12: 3937.51 | U12: 3937.51 | V12: 3937.51 | W12: 3937.51 | X12: 3937.51 | Y12: 3937.51 | Z12: 3937.51 | AA12: 3937.51 | AB12: 3937.51 | AC12: 3937.51 | AD12: 3937.51 | AE12: 3937.51 | AF12: 3937.51 | AG12: 3937.51 | AH12: 3937.51 | AI12: 3937.51 | AJ12: 3937.51 | AK12: 3937.51 | AL12: 3937.51 | AM12: 3937.51
A13: Barnum | B13: Taylor | D13: Yes | E13: 1799.93 | F13: 1799.93 | G13: 1799.93 | H13: 1799.93 | I13: 1799.93 | J13: 1799.93 | K13: 1799.93 | L13: 1799.93 | M13: 1799.93 | N13: 1799.93 | O13: 1799.93 | P13: 1799.93 | Q13: 1799.93 | R13: 1799.93 | S13: 1799.93 | T13: 1799.93 | U13: 1799.93 | V13: 1799.93 | W13: 1799.93 | X13: 1799.93 | Y13: 1799.93 | Z13: 1799.93 | AA13: 1799.93 | AB13: 1799.93 | AC13: 1799.93 | AD13: 1799.93 | AE13: 1799.93 | AF13: 1799.93 | AG13: 1799.93 | AH13: 1799.93 | AI13: 1799.93 | AJ13: 1799.93 | AK13: 1799.93 | AL13: 1799.93 | AM13: 1799.93
A14: Sullivan | B14: Taylor | D14: Yes | E14: 1575 | F14: 1575 | G14: 1575 | H14: 1575 | I14: 1575 | J14: 1575 | K14: 1575 | L14: 1575 | M14: 1575 | N14: 1575 | O14: 1575 | P14: 1575 | Q14: 1575 | R14: 1575 | S14: 1575 | T14: 1575 | U14: 1575 | V14: 1575 | W14: 1575 | X14: 1575 | Y14: 1575 | Z14: 1575 | AA14: 1575 | AB14: 1575 | AC14: 1575 | AD14: 1575 | AE14: 1575 | AF14: 1575 | AG14: 1575 | AH14: 1575 | AI14: 1575 | AJ14: 1575 | AK14: 1575 | AL14: 1575 | AM14: 1575
A15: Contractors (2 paid on last Friday of each month) | G15: 6000 | L15: 6000 | P15: 6000 | T15: 6000 | Y15: 6000 | AE15: 6001 | AG15: 6001 | AM15: 6002
A16: New Employees | V16: =(180000/26) -> 6923.0769 | W16: =(180000/26) -> 6923.0769 | X16: =(180000/26) -> 6923.0769 | Y16: =(180000/26) -> 6923.0769 | Z16: =(180000/26) -> 6923.0769 | AA16: =(180000/26) -> 6923.0769 | AB16: =(180000/26) -> 6923.0769 | AC16: =(180000/26) -> 6923.0769 | ... AM16: =(180000/26) -> 6923.0769
A17: Dave | AD17: =AD12 -> 3937.51 | AE17: =AE12 -> 3937.51 | AF17: =AF12 -> 3937.51 | AG17: =AG12 -> 3937.51 | AH17: =AH12 -> 3937.51 | AI17: =AI12 -> 3937.51 | AJ17: =AJ12 -> 3937.51 | AK17: =AK12 -> 3937.51 | ... AM17: =AM12 -> 3937.51
A18: Commisions Paid | K18: 15680.22 | W18: 24000 | AC18: 26000 | AK18: 26001
B19: David | U19: 3937.51 | V19: 3937.51 | W19: 3937.51 | X19: 3937.51 | Y19: 3937.51 | Z19: 3937.51 | AA19: 3937.51 | AB19: 3937.51 | AC19: 3937.51 | AD19: 3937.51 | AE19: 3937.51 | AF19: 3937.51 | AG19: 3937.51 | AH19: 3937.51 | AI19: 3937.51 | AJ19: 3937.51 | AK19: 3937.51 | AL19: 3937.51 | AM19: 3937.51
U20: =(160000/52)*1.25 -> 3846.1538 | V20: =(160000/52)*1.25 -> 3846.1538 | W20: =(160000/52)*1.25 -> 3846.1538 | X20: =(160000/52)*1.25 -> 3846.1538 | Y20: =(160000/52)*1.25 -> 3846.1538 | Z20: =(160000/52)*1.25 -> 3846.1538 | AA20: =(160000/52)*1.25 -> 3846.1538 | AB20: =(160000/52)*1.25 -> 3846.1538 | ... AM20: =(160000/52)*1.25 -> 3846.1538
A21: Distributions | O21: 10000 | S21: 10000 | W21: 10000 | AA21: 10000 | AE21: 10000 | AI21: 10001 | AM21: 10001
A22: TOTALS | E22: =SUM(E2:E21) -> 19700.74 | F22: =SUM(F2:F21) -> 23165.1 | G22: =SUM(G2:G21) -> 28853.76 | H22: =SUM(H2:H21) -> 24776.837 | I22: =SUM(I2:I21) -> 24776.837 | J22: =SUM(J2:J21) -> 24776.837 | K22: =SUM(K2:K21) -> 40457.057 | L22: =SUM(L2:L21) -> 30372.76 | ... AM22: =SUM(AM2:AM21) -> 57611.588
A25: Shawn | B25: 37657.68
A26: Dave | B26: 30927.26
